tor_http/__init__.py
tor_http/_bundled.py
tor_http/_download.py
tor_http/_paths.py
tor_http/_runtime.py
tor_http/_tor.py
tor_http/tor_http.py
tor_http-0.0.1.dist-info/LICENSE.md
tor_http-0.0.1.dist-info/METADATA
tor_http-0.0.1.dist-info/WHEEL
tor_http-0.0.1.dist-info/top_level.txt
tor_http-0.0.1.dist-info/RECORD
