Metadata-Version: 2.1
Name: tor-http
Version: 0.0.1
Summary: Async httpx wrapper that auto-manages a local Tor process (downloads Tor on first run).
Author: S M Abrar Jahin
License: MIT License
Project-URL: Homepage, https://github.com/AbrarJahin/tor-http
Project-URL: Issues, https://github.com/AbrarJahin/tor-http/issues
Keywords: httpx,tor,stem,socks,async,privacy,proxy
Requires-Python: >=3.8
License-File: LICENSE.md
Requires-Dist: httpx[socks]>=0.27.0
Requires-Dist: stem>=1.8.2
Requires-Dist: platformdirs>=4.0.0
Provides-Extra: dev
Requires-Dist: pytest>=8.0; extra == "dev"
Requires-Dist: ruff>=0.6; extra == "dev"
Requires-Dist: mypy>=1.10; extra == "dev"
